flowtrace/__init__.py
flowtrace/asyncio_support.py
flowtrace/config.py
flowtrace/core.py
flowtrace/decorators.py
flowtrace/events.py
flowtrace/monitoring.py
flowtrace/session.py
flowtrace/formatters/__init__.py
flowtrace/formatters/async_tree.py
flowtrace/formatters/formatters.py
flowtrace-0.5.0.dist-info/licenses/LICENSE
flowtrace-0.5.0.dist-info/METADATA
flowtrace-0.5.0.dist-info/WHEEL
flowtrace-0.5.0.dist-info/top_level.txt
flowtrace-0.5.0.dist-info/RECORD
