Metadata-Version: 2.4
Name: flowtrace
Version: 0.5.0
Summary: System-level execution tracer for Python 3.12+ (PEP 669)
Author-email: Alexandr153 <boss191105@bk.ru>
License: MIT
Project-URL: Homepage, https://github.com/Python-Fork/FlowTrace
Project-URL: Documentation, https://github.com/Python-Fork/FlowTrace/blob/main/README.md
Project-URL: Issues, https://github.com/Python-Fork/FlowTrace/issues
Keywords: python,monitoring,tracing,PEP669,async
Classifier: Programming Language :: Python :: 3 :: Only
Classifier: Programming Language :: Python :: 3.12
Classifier: Programming Language :: Python :: 3.13
Classifier: Programming Language :: Python :: 3.14
Classifier: Development Status :: 4 - Beta
Classifier: Intended Audience :: Developers
Classifier: Topic :: Software Development :: Debuggers
Requires-Python: >=3.12
License-File: LICENSE
Dynamic: license-file
